prevh/_PrevhClassifier.py
prevh/__init__.py
prevh/Assets/Distances.py
prevh/Assets/Predict.py
prevh/Assets/__init__.py
prevh/Assets/Dataset/Dataset.py
prevh/Assets/Dataset/Split.py
prevh/Assets/Dataset/__init__.py
prevh/Assets/Evaluator/Evaluation.py
prevh/Assets/Evaluator/Metrics.py
prevh/Assets/Evaluator/__init__.py
prevh/Assets/Utils/ErrorHandler.py
prevh/Assets/Utils/Static.py
prevh/Assets/Utils/__init__.py
prevhlib-0.2.0.dist-info/LICENSE
prevhlib-0.2.0.dist-info/METADATA
prevhlib-0.2.0.dist-info/WHEEL
prevhlib-0.2.0.dist-info/top_level.txt
prevhlib-0.2.0.dist-info/RECORD
