Metadata-Version: 2.1
Name: prevhlib
Version: 0.2.0
Summary: Data Mining package implementing the PrevhClassifier algorithm.
Home-page: https://github.com/JCGCosta/Prevh
Author: Júlio César Guimarães Costa
Author-email: juliocesargcosta123@gmail.com
License: GNU General Public License v3 (GPLv3)
Keywords: DataMining
Classifier: Development Status :: 3 - Alpha
Classifier: Intended Audience :: Developers
Classifier: Operating System :: Microsoft :: Windows :: Windows 11
Classifier: License :: OSI Approved :: GNU General Public License v3 (GPLv3)
Classifier: Programming Language :: Python :: 3.11
License-File: LICENSE
Requires-Dist: numpy
Requires-Dist: pandas
Requires-Dist: matplotlib
Requires-Dist: scikit-learn
Requires-Dist: seaborn
